Metadata-Version: 2.1
Name: gawain
Version: 0.0.5
Summary: Asyncio booru wrapper with spell blocker
Home-page: https://github.com/sinkaroid/gawain
Author: sinkaroid
Author-email: anakmancasan@gmail.com
License: MIT
Keywords: booru,wrapper
Platform: UNKNOWN
